parallax_maker/__init__.py
parallax_maker/automatic1111.py
parallax_maker/camera.py
parallax_maker/clientside.py
parallax_maker/comfyui.py
parallax_maker/components.py
parallax_maker/constants.py
parallax_maker/controller.py
parallax_maker/depth.py
parallax_maker/gltf.py
parallax_maker/gltf_cli.py
parallax_maker/inpainting.py
parallax_maker/instance.py
parallax_maker/segmentation.py
parallax_maker/setup_dev.py
parallax_maker/slice.py
parallax_maker/stabilityai.py
parallax_maker/test_automatic1111.py
parallax_maker/test_components.py
parallax_maker/test_constants.py
parallax_maker/test_controller.py
parallax_maker/test_gltf.py
parallax_maker/test_inpainting.py
parallax_maker/test_instance.py
parallax_maker/test_segmentation.py
parallax_maker/test_stabilityai.py
parallax_maker/test_upscaler.py
parallax_maker/test_utils.py
parallax_maker/test_webui.py
parallax_maker/upscaler.py
parallax_maker/utils.py
parallax_maker/webui.py
parallax_maker/assets/css/features.css
parallax_maker/assets/css/tailwind_compiled.css
parallax_maker/assets/scripts/utility.js
parallax_maker-1.0.3.dist-info/licenses/LICENSE
parallax_maker-1.0.3.dist-info/METADATA
parallax_maker-1.0.3.dist-info/WHEEL
parallax_maker-1.0.3.dist-info/entry_points.txt
parallax_maker-1.0.3.dist-info/top_level.txt
parallax_maker-1.0.3.dist-info/RECORD
