Metadata-Version: 2.4
Name: parallax-maker
Version: 1.0.3
Summary: A workflow for turning images into 2.5D animations with depth-based segmentation and inpainting
Author-email: Niels Provos <niels@provos.org>
License-Expression: AGPL-3.0-or-later
Project-URL: Homepage, https://github.com/provos/parallax-maker
Project-URL: Documentation, https://github.com/provos/parallax-maker#readme
Project-URL: Repository, https://github.com/provos/parallax-maker
Project-URL: Issues, https://github.com/provos/parallax-maker/issues
Keywords: computer-vision,depth-estimation,image-segmentation,3d-animation,gltf,dash,stable-diffusion
Classifier: Development Status :: 4 - Beta
Classifier: Intended Audience :: Developers
Classifier: Intended Audience :: End Users/Desktop
Classifier: Operating System :: OS Independent
Classifier: Programming Language :: Python :: 3
Classifier: Programming Language :: Python :: 3.10
Classifier: Programming Language :: Python :: 3.11
Classifier: Programming Language :: Python :: 3.12
Classifier: Topic :: Multimedia :: Graphics :: 3D Modeling
Classifier: Topic :: Multimedia :: Graphics :: Graphics Conversion
Classifier: Topic :: Scientific/Engineering :: Image Processing
Classifier: Topic :: Scientific/Engineering :: Artificial Intelligence
Requires-Python: >=3.10
License-File: LICENSE
Requires-Dist: dash==2.17.0
Requires-Dist: dash_extensions==1.0.14
Requires-Dist: numpy==1.26.4
Requires-Dist: Pillow>=10.3.0
Requires-Dist: pygltflib==1.16.2
Requires-Dist: torch>=2.2.2
Requires-Dist: torchvision>=0.17.2
Requires-Dist: opencv-python>=4.9.0
Requires-Dist: timm==0.6.12
Requires-Dist: diffusers[torch]>=0.29.0
Requires-Dist: transformers>=4.40
Requires-Dist: orjson>=3.10.1
Requires-Dist: numba>=0.59.1
Requires-Dist: websocket-client>=1.8.0
Requires-Dist: scipy>=1.13.1
Provides-Extra: dev
Requires-Dist: pytest; extra == "dev"
Requires-Dist: pytest-cov; extra == "dev"
Requires-Dist: black; extra == "dev"
Requires-Dist: flake8; extra == "dev"
Requires-Dist: mypy; extra == "dev"
Requires-Dist: pre-commit; extra == "dev"
Dynamic: license-file
